azure/ai/language/conversations/__init__.py
azure/ai/language/conversations/_client.py
azure/ai/language/conversations/_configuration.py
azure/ai/language/conversations/_patch.py
azure/ai/language/conversations/_serialization.py
azure/ai/language/conversations/_vendor.py
azure/ai/language/conversations/_version.py
azure/ai/language/conversations/py.typed
azure/ai/language/conversations/_operations/__init__.py
azure/ai/language/conversations/_operations/_operations.py
azure/ai/language/conversations/_operations/_patch.py
azure/ai/language/conversations/aio/__init__.py
azure/ai/language/conversations/aio/_client.py
azure/ai/language/conversations/aio/_configuration.py
azure/ai/language/conversations/aio/_patch.py
azure/ai/language/conversations/aio/_vendor.py
azure/ai/language/conversations/aio/_operations/__init__.py
azure/ai/language/conversations/aio/_operations/_operations.py
azure/ai/language/conversations/aio/_operations/_patch.py
azure/ai/language/conversations/authoring/__init__.py
azure/ai/language/conversations/authoring/_client.py
azure/ai/language/conversations/authoring/_configuration.py
azure/ai/language/conversations/authoring/_patch.py
azure/ai/language/conversations/authoring/_serialization.py
azure/ai/language/conversations/authoring/_vendor.py
azure/ai/language/conversations/authoring/_version.py
azure/ai/language/conversations/authoring/py.typed
azure/ai/language/conversations/authoring/_operations/__init__.py
azure/ai/language/conversations/authoring/_operations/_operations.py
azure/ai/language/conversations/authoring/_operations/_patch.py
azure/ai/language/conversations/authoring/aio/__init__.py
azure/ai/language/conversations/authoring/aio/_client.py
azure/ai/language/conversations/authoring/aio/_configuration.py
azure/ai/language/conversations/authoring/aio/_patch.py
azure/ai/language/conversations/authoring/aio/_vendor.py
azure/ai/language/conversations/authoring/aio/_operations/__init__.py
azure_ai_language_conversations-1.1.0.dist-info/LICENSE
azure_ai_language_conversations-1.1.0.dist-info/METADATA
azure_ai_language_conversations-1.1.0.dist-info/WHEEL
azure_ai_language_conversations-1.1.0.dist-info/top_level.txt
azure_ai_language_conversations-1.1.0.dist-info/RECORD
